microtest/__init__.py
microtest/__main__.py
microtest/api.py
microtest/assertion.py
microtest/logging.py
microtest/objects.py
microtest/scanner.py
microtest/utils.py
microtest/core/__init__.py
microtest/core/utils.py
microtest/docs/__init__.py
microtest/docs/__main__.py
microtest_framework-1.0.1.dist-info/LICENSE.txt
microtest_framework-1.0.1.dist-info/METADATA
microtest_framework-1.0.1.dist-info/WHEEL
microtest_framework-1.0.1.dist-info/top_level.txt
microtest_framework-1.0.1.dist-info/RECORD
