Metadata-Version: 2.1
Name: microtest-framework
Version: 1.0.1
Summary: Simple but powerful testing framework for Python
Home-page: https://github.com/varajala/microtest
Author: Valtteri Rajalainen
Author-email: rajalainen.valtteri@gmail.com
License: UNKNOWN
Project-URL: Documentation, https://varajala.github.io/microtest/docs/
Platform: UNKNOWN
Classifier: Programming Language :: Python :: 3
Classifier: License :: OSI Approved :: MIT License
Classifier: Operating System :: OS Independent
Classifier: Topic :: Software Development :: Testing
Classifier: Topic :: Software Development :: Testing :: Unit
Classifier: Topic :: Utilities
Requires-Python: >=3.7
License-File: LICENSE.txt
